{
  "latest_version": "1.1.2",
  "versions": [
    "1.0",
    "1.1.2"
  ],
  "hosts": [
    {
      "id": "gdrive_primary",
      "name": "Google Drive",
      "links": {
        "1.0_1.1.2": "1ABC123XYZ456DEF789"
      }
    },
    {
      "id": "gdrive_mirror",
      "name": "Google Drive Mirror",
      "links": {
        "1.0_1.1.2": "1MIRROR123ABC456XYZ"
      }
    }
  ],
  "update_sizes": {
    "1.0_1.1.2": "500 MB"
  },
  "host_preference_order": [
    "gdrive_primary",
    "gdrive_mirror"
  ],
  "manifest_links": {
    "1.0": "https://raw.githubusercontent.com/aman71711/CRICKET26_Utility/main/manifests/manifest_v1.0.json",
    "1.1.2": "https://raw.githubusercontent.com/aman71711/CRICKET26_Utility/main/manifests/manifest_v1.1.2.json"
  },
  "fallback_links": {
    "1.0_1.1.2": {
      "url": "https://direct-download-server.com/cricket26/updates/cricket26_v1.0_to_v1.1.2.zip",
      "message": "Primary download sources unavailable. Using fallback server for v1.0 → v1.1.2 update."
    }
  }
}
